{"ExtraData":null,"Type":0,"Version":"1.0.0","Hashes":{"Files":[{"RelativePath":"ModConfig.json","Hash":16344586809880900278},{"RelativePath":"restored return healing.png","Hash":2700840246067057661},{"RelativePath":"FEmulator\\BF\\h15_18.flow","Hash":3784800364047068161},{"RelativePath":"FEmulator\\PAK\\field2d\\bg\\b15_18.abin\\h15_18.bf","Hash":17241709254077376921}]},"IgnoreRegexes":[".*\\.json","p3ppc\\.qol\\.returnheal\\.nuspec","p3ppc\\.qol\\.returnheal\\.ReleaseMetadata\\.json"],"IncludeRegexes":["ModConfig\\.json","\\.deps\\.json","\\.runtimeconfig\\.json"],"DeltaData":null}